ilp_decoder/__init__.py
ilp_decoder/ilp.py
ilp_decoder/py.typed
ilp_decoder/sinter.py
ilp_decoder/utils.py
ilp_decoder-0.2.2.dist-info/METADATA
ilp_decoder-0.2.2.dist-info/WHEEL
ilp_decoder-0.2.2.dist-info/licenses/LICENSE
ilp_decoder-0.2.2.dist-info/RECORD
