Metadata-Version: 2.4
Name: ilp-decoder
Version: 0.2.2
Summary: An implementation of ILP decoders for quantum error correction.
Author-email: Yiming Zhang <zhangyiming21@mail.ustc.edu.cn>
License-File: LICENSE
Requires-Python: >=3.10
Requires-Dist: cvxpy>=1.6.4
Requires-Dist: highspy>=1.10.0
Requires-Dist: sinter>=1.14.0
Requires-Dist: stim>=1.14.0
